[
  {
    "idAdm": "funcionario",
    "codigoDoUser": 7171.0,
    "loginF": "y",
    "senhaF": "y",
    "codigoDoCliente": 0.0,
    "telefone": "y",
    "email": "y",
    "rua": "y",
    "bairro": "y",
    "numeroCasa": "y",
    "cep": "y",
    "cidade": "y",
    "nome": "y",
    "cpf": "y"
  },
  {
    "idAdm": "funcionario",
    "codigoDoUser": 1339,
    "loginF": "123",
    "senhaF": "123",
    "codigoDoCliente": 0,
    "telefone": "55-55555-5555",
    "email": "dfdfdfd@gamil.cm",
    "rua": "T",
    "bairro": "999999",
    "numeroCasa": "66666",
    "cep": "39100-000",
    "cidade": "DMT",
    "nome": "Felipe ",
    "cpf": "555-555-555-55"
  }
]